subway/__init__.py
subway/bootstrap.py
subway/cli.py
subway/config.py
subway/cons.py
subway/entry.py
subway/exceptions.py
subway/framework.py
subway/htree.py
subway/inits.py
subway/utils.py
subway/workflow.py
subway/components/__init__.py
subway/components/genfiles.py
subway/components/slurmoo.py
subway/examples/__init__.py
subway/examples/rgdslurm.py
subway/examples/rglocal.py
subway/examples/rgslurm.py
subway/plugins/__init__.py
subway/plugins/debug.py
subway/plugins/dslurm.py
subway/plugins/slurm.py
subway/plugins/sslurm.py
hpcsubway-0.0.2.dist-info/LICENSE
hpcsubway-0.0.2.dist-info/METADATA
hpcsubway-0.0.2.dist-info/WHEEL
hpcsubway-0.0.2.dist-info/entry_points.txt
hpcsubway-0.0.2.dist-info/top_level.txt
hpcsubway-0.0.2.dist-info/RECORD
